django_numericfieldlistfilter-0.1.dist-info/DESCRIPTION.rst
django_numericfieldlistfilter-0.1.dist-info/METADATA
django_numericfieldlistfilter-0.1.dist-info/RECORD
django_numericfieldlistfilter-0.1.dist-info/WHEEL
django_numericfieldlistfilter-0.1.dist-info/metadata.json
django_numericfieldlistfilter-0.1.dist-info/top_level.txt
djangonumericfieldlistfilter/__init__.py
djangonumericfieldlistfilter/filters.py
djangonumericfieldlistfilter/options.py
djangonumericfieldlistfilter/static/admin/css/admin/NumericFieldListFilter.css
djangonumericfieldlistfilter/static/admin/js/admin/NumericFieldListFilter.js
djangonumericfieldlistfilter/templates/admin/numericfieldlistfilter.html
