Metadata-Version: 2.0
Name: django-numericfieldlistfilter
Version: 0.1
Summary: A NumericFieldListFilter for Django admin
Home-page: https://github.com/jbkkd/django-numericfieldlistfilter
Author: Omer Korner
Author-email: omerkorner@gmail.com
License: MIT
Keywords: django plugin fieldlistfilter
Platform: UNKNOWN
Classifier: Development Status :: 4 - Beta
Classifier: Intended Audience :: Developers
Classifier: Topic :: Software Development :: Libraries :: Python Modules
Classifier: License :: OSI Approved :: MIT License
Classifier: Programming Language :: Python
Classifier: Programming Language :: Python :: 2.7
Classifier: Programming Language :: Python :: 3.4
Classifier: Programming Language :: Python :: 3.5
Classifier: Framework :: Django
Classifier: Framework :: Django :: 1.9
Classifier: Operating System :: OS Independent
